README.md
setup.py
kivycv/audio.py
kivycv/audiorecorder.py
kivycv/camerawithmic.py
kivycv/custom_camera.py
kivycv/kivycamera.py
kivycv/micphone.py
kivycv/qrcodereader.py
kivycv/register.py
kivycv/version.py
kivycv.egg-info/PKG-INFO
kivycv.egg-info/SOURCES.txt
kivycv.egg-info/dependency_links.txt
kivycv.egg-info/requires.txt
kivycv.egg-info/top_level.txt
kivycv/image_processing/__init__.py
kivycv/image_processing/image_processing.py
kivycv/image_processing/cascades/haarcascade_frontalface_default.xml